odoo/addons/mrp_unbuild_tracked_raw_material/README.rst
odoo/addons/mrp_unbuild_tracked_raw_material/__init__.py
odoo/addons/mrp_unbuild_tracked_raw_material/__manifest__.py
odoo/addons/mrp_unbuild_tracked_raw_material/i18n/it.po
odoo/addons/mrp_unbuild_tracked_raw_material/i18n/mrp_unbuild_tracked_raw_material.pot
odoo/addons/mrp_unbuild_tracked_raw_material/i18n/pt_BR.po
odoo/addons/mrp_unbuild_tracked_raw_material/models/__init__.py
odoo/addons/mrp_unbuild_tracked_raw_material/models/product.py
odoo/addons/mrp_unbuild_tracked_raw_material/models/unbuild.py
odoo/addons/mrp_unbuild_tracked_raw_material/readme/CONFIGURE.rst
odoo/addons/mrp_unbuild_tracked_raw_material/readme/CONTRIBUTORS.rst
odoo/addons/mrp_unbuild_tracked_raw_material/readme/DESCRIPTION.rst
odoo/addons/mrp_unbuild_tracked_raw_material/readme/ROADMAP.rst
odoo/addons/mrp_unbuild_tracked_raw_material/readme/USAGE.rst
odoo/addons/mrp_unbuild_tracked_raw_material/static/description/icon.png
odoo/addons/mrp_unbuild_tracked_raw_material/static/description/index.html
odoo/addons/mrp_unbuild_tracked_raw_material/tests/__init__.py
odoo/addons/mrp_unbuild_tracked_raw_material/tests/test_unbuild.py
odoo/addons/mrp_unbuild_tracked_raw_material/views/product_view.xml
odoo12_addon_mrp_unbuild_tracked_raw_material-12.0.1.0.0.99.dev10.dist-info/METADATA
odoo12_addon_mrp_unbuild_tracked_raw_material-12.0.1.0.0.99.dev10.dist-info/WHEEL
odoo12_addon_mrp_unbuild_tracked_raw_material-12.0.1.0.0.99.dev10.dist-info/top_level.txt
odoo12_addon_mrp_unbuild_tracked_raw_material-12.0.1.0.0.99.dev10.dist-info/RECORD
